<xml xmlns="http://www.w3.org/1999/xhtml"><block type="insert" id="7" inline="false" x="0" y="0"><mutation set="8" colorhue="115"></mutation><value name="set0"><block type="to" id="8" inline="false"><mutation colour="15"></mutation><value name="A"><block type="tables_and_colums_var" id="9"><mutation tabele="products" column="productCode" colourhue_="15"></mutation><field name="tabele">products</field><field name="Column">productCode</field></block></value><value name="B"><block type="string" id="10"><field name="String">zelt</field></block></value></block></value><value name="set1"><block type="to" id="11" inline="false"><mutation colour="15"></mutation><value name="A"><block type="tables_and_colums_var" id="12"><mutation tabele="products" column="productName" colourhue_="15"></mutation><field name="tabele">products</field><field name="Column">productName</field></block></value><value name="B"><block type="string" id="13"><field name="String">wurfzeltblau</field></block></value></block></value><value name="set2"><block type="to" id="14" inline="false"><mutation colour="15"></mutation><value name="A"><block type="tables_and_colums_var" id="15"><mutation tabele="products" column="productLine" colourhue_="15"></mutation><field name="tabele">products</field><field name="Column">productLine</field></block></value><value name="B"><block type="string" id="16"><field name="String">outdoor</field></block></value></block></value><value name="set3"><block type="to" id="17" inline="false"><mutation colour="15"></mutation><value name="A"><block type="tables_and_colums_var" id="18"><mutation tabele="products" column="productScale" colourhue_="15"></mutation><field name="tabele">products</field><field name="Column">productScale</field></block></value><value name="B"><block type="string" id="19"><field name="String">outdoor</field></block></value></block></value><value name="set4"><block type="to" id="20" inline="false"><mutation colour="15"></mutation><value name="A"><block type="tables_and_colums_var" id="21"><mutation tabele="products" column="productVendor" colourhue_="15"></mutation><field name="tabele">products</field><field name="Column">productVendor</field></block></value><value name="B"><block type="string" id="22"><field name="String">sportgmbh</field></block></value></block></value><value name="set5"><block type="to" id="23" inline="false"><mutation colour="15"></mutation><value name="A"><block type="tables_and_colums_var" id="24"><mutation tabele="products" column="productDescription" colourhue_="15"></mutation><field name="tabele">products</field><field name="Column">productDescription</field></block></value><value name="B"><block type="string" id="25"><field name="String">zelt</field></block></value></block></value><value name="set6"><block type="to" id="26" inline="false"><mutation colour="255"></mutation><value name="A"><block type="tables_and_colums_var" id="27"><mutation tabele="products" column="quantityInStock" colourhue_="255"></mutation><field name="tabele">products</field><field name="Column">quantityInStock</field></block></value><value name="B"><block type="num" id="28"><field name="NUM">200</field></block></value></block></value><value name="set7"><block type="to" id="29" inline="false"><mutation colour="255"></mutation><value name="A"><block type="tables_and_colums_var" id="30"><mutation tabele="products" column="buyPrice" colourhue_="255"></mutation><field name="tabele">products</field><field name="Column">buyPrice</field></block></value><value name="B"><block type="num" id="31"><field name="NUM">120</field></block></value></block></value><value name="set8"><block type="to" id="32" inline="false"><mutation colour="255"></mutation><value name="A"><block type="tables_and_colums_var" id="33"><mutation tabele="products" column="MSRP" colourhue_="255"></mutation><field name="tabele">products</field><field name="Column">MSRP</field></block></value><value name="B"><block type="num" id="34"><field name="NUM">220</field></block></value></block></value></block></xml>